roshareclient/__init__.py
roshareclient/client/__init__.py
roshareclient/client/api.py
roshareclient/client/cons.py
roshareclient/test/test_dataapi.py
shihua_roshareclient-0.1.2.dist-info/METADATA
shihua_roshareclient-0.1.2.dist-info/WHEEL
shihua_roshareclient-0.1.2.dist-info/top_level.txt
shihua_roshareclient-0.1.2.dist-info/RECORD
