Metadata-Version: 2.1
Name: shihua-roshareclient
Version: 0.1.2
Summary: RoShareClient is a python sdk with chinese stock data client
Home-page: https://github.com/redblue0216/RoShare
Author: shihua
Author-email: 15021408795@163.com
License: MIT
Requires-Python: >=3.9.13
